dpr/__init__.py
dpr/register.py
dpr/utils.py
dpr/scripts/__init__.py
dpr/scripts/dpr.py
dpr/scripts/dpr_make_fancy_graph.py
dpr-0.2.2.dist-info/LICENSE
dpr-0.2.2.dist-info/METADATA
dpr-0.2.2.dist-info/WHEEL
dpr-0.2.2.dist-info/entry_points.txt
dpr-0.2.2.dist-info/top_level.txt
dpr-0.2.2.dist-info/RECORD
