Metadata-Version: 2.1
Name: dpr
Version: 0.2.2
Summary: Implementation of "Reducing variability in along-tract analysis with diffusion profile realignment".
Author-email: Samuel St-Jean <firstname.st_jean@med.lu.se>
License: MIT License
Project-URL: Homepage, https://github.com/samuelstjean/dpr
Project-URL: Documentation, https://dpr.readthedocs.io/en/latest/
Project-URL: Changelog, https://github.com/samuelstjean/dpr/blob/master/CHANGELOG.md
Requires-Python: >=3.9
License-File: LICENSE
Requires-Dist: numpy>=1.15
Requires-Dist: scipy>=1.2
Requires-Dist: matplotlib>=3.0
